portrayt/__init__.py
portrayt/configuration/__init__.py
portrayt/configuration/main_schema.py
portrayt/configuration/prompt_interpolation_animation.py
portrayt/configuration/prompt_variations.py
portrayt/configuration/rendering.py
portrayt/generators/__init__.py
portrayt/generators/base_generator.py
portrayt/generators/interpolation_animation_generator.py
portrayt/generators/variation_generator.py
portrayt/interface/__init__.py
portrayt/interface/main_ui.py
portrayt/main.py
portrayt/renderers/__init__.py
portrayt/renderers/base_renderer.py
portrayt/renderers/crop_utils.py
portrayt/renderers/inky_renderer.py
portrayt/renderers/opencv_renderer.py
portrayt-1.0.0.dist-info/entry_points.txt
portrayt-1.0.0.dist-info/LICENSE
portrayt-1.0.0.dist-info/WHEEL
portrayt-1.0.0.dist-info/METADATA
portrayt-1.0.0.dist-info/RECORD
