Metadata-Version: 2.1
Name: portrayt
Version: 1.0.0
Summary: This project combines e-paper, raspberry pi's, and StableDiffusion to make a picture frame that portrays anything you ask of it.
License: MIT
Author: Alex Thiele
Author-email: apocthiel@gmail.com
Requires-Python: >=3.8,<4.0
Classifier: License :: OSI Approved :: MIT License
Classifier: Programming Language :: Python :: 3
Classifier: Programming Language :: Python :: 3.8
Classifier: Programming Language :: Python :: 3.9
Classifier: Programming Language :: Python :: 3.10
Provides-Extra: opencv
Requires-Dist: RPi.GPIO (>=0.7.1,<0.8.0)
Requires-Dist: gradio (>=3.3,<4.0)
Requires-Dist: inky (>=1.3.2,<2.0.0)
Requires-Dist: opencv-python (>=4.6.0.66,<5.0.0.0); extra == "opencv"
Requires-Dist: pydantic (>=1.10.2,<2.0.0)
Requires-Dist: replicate (==0.0.1a16)
